{"id":"qJVQpSGspGEf5Rpn2u9lB","title":"Gen Ed","desc":"","updated":1640330126358,"created":1640209729278,"tags":["TODO","school"],"custom":{},"fname":"gen-ed","type":"note","vault":{"fsPath":".","name":"vault","selfContained":true},"contentHash":"dbae215d8c0748b5efa0342dd6b76517","links":[{"type":"frontmatterTag","from":{"fname":"gen-ed","id":"qJVQpSGspGEf5Rpn2u9lB","vaultName":"vault"},"value":"tags.TODO","alias":"TODO","xvault":false,"to":{"fname":"tags.TODO"}},{"type":"frontmatterTag","from":{"fname":"gen-ed","id":"qJVQpSGspGEf5Rpn2u9lB","vaultName":"vault"},"value":"tags.school","alias":"school","xvault":false,"to":{"fname":"tags.school"}}],"anchors":{},"children":["ykJFSHBzDetVjhB8t7XeY"],"parent":"ik5Bi5OCTsmfKfq5JQtEB","data":{}}
